magent2/libmagent.so
magent2/gridworld.py
magent2/environment.py
magent2/__init__.py
magent2/testlib
magent2/render.py
magent2/c_lib.py
magent2/utility.py
magent2/environments/battle_v4.py
magent2/environments/adversarial_pursuit_v4.py
magent2/environments/combined_arms_v6.py
magent2/environments/__init__.py
magent2/environments/gather_v5.py
magent2/environments/battlefield_v5.py
magent2/environments/magent_env.py
magent2/environments/tiger_deer_v4.py
magent2/environments/tiger_deer/__init__.py
magent2/environments/tiger_deer/tiger_deer.py
magent2/environments/battle/battle.py
magent2/environments/battle/__init__.py
magent2/environments/combined_arms/__init__.py
magent2/environments/combined_arms/combined_arms.py
magent2/environments/gather/gather.py
magent2/environments/gather/__init__.py
magent2/environments/battlefield/battlefield.py
magent2/environments/battlefield/__init__.py
magent2/environments/adversarial_pursuit/adversarial_pursuit.py
magent2/environments/adversarial_pursuit/__init__.py
magent2/builtin/__init__.py
magent2/builtin/config/battle.py
magent2/builtin/config/forest.py
magent2/builtin/config/double_attack.py
magent2/builtin/config/__init__.py
magent2/builtin/config/pursuit.py
magent2-0.3.3.dist-info/RECORD
magent2-0.3.3.dist-info/WHEEL
magent2-0.3.3.dist-info/LICENSE
magent2-0.3.3.dist-info/top_level.txt
magent2-0.3.3.dist-info/METADATA
