Metadata-Version: 2.1
Name: magent2
Version: 0.3.3
Summary: Multi-Agent Reinforcement Learning environments with very large numbers of agents.
Author-email: Farama Foundation <contact@farama.org>
License: MIT License
Project-URL: Homepage, https://farama.org
Project-URL: Repository, https://github.com/Farama-Foundation/MAgent2
Project-URL: Documentation, https://magent2.farama.org
Project-URL: Bug Report, https://github.com/Farama-Foundation/MAgent2/issues
Keywords: Reinforcement Learning,game,RL,AI
Classifier: Development Status :: 4 - Beta
Classifier: License :: OSI Approved :: MIT License
Classifier: Programming Language :: Python :: 3
Classifier: Programming Language :: Python :: 3.8
Classifier: Programming Language :: Python :: 3.9
Classifier: Programming Language :: Python :: 3.10
Classifier: Programming Language :: Python :: 3.11
Classifier: Intended Audience :: Science/Research
Classifier: Topic :: Scientific/Engineering :: Artificial Intelligence
Requires-Python: >=3.8
License-File: LICENSE
Requires-Dist: numpy <2.0,>=1.21.0
Requires-Dist: pygame >=2.1.0
Requires-Dist: pettingzoo >=1.23.1
